setup.py
sunnyday_student_2024/__init__.py
sunnyday_student_2024/sunnyday_student_2024.py
sunnyday_student_2024.egg-info/PKG-INFO
sunnyday_student_2024.egg-info/SOURCES.txt
sunnyday_student_2024.egg-info/dependency_links.txt
sunnyday_student_2024.egg-info/requires.txt
sunnyday_student_2024.egg-info/top_level.txt