Metadata-Version: 1.1
Name: sunnyday-student-2024
Version: 2.0.0
Summary: Weather forecast data
Home-page: https://example.com
Author: Steve Student
Author-email: your.email@example.com
License: MIT
Keywords: weather,forecast,openweather
Platform: UNKNOWN
Classifier: Development Status :: 3 - Alpha
Classifier: Intended Audience :: Developers
Classifier: Topic :: Software Development :: Build Tools
Classifier: License :: OSI Approved :: MIT License
Classifier: Programming Language :: Python :: 3.9
